lumi/__init__.py
lumi/api.py
lumi/enums.py
lumi/helpers.py
lumi/server.py
lumi-1.0.11.dist-info/LICENSE.MD
lumi-1.0.11.dist-info/METADATA
lumi-1.0.11.dist-info/WHEEL
lumi-1.0.11.dist-info/top_level.txt
lumi-1.0.11.dist-info/RECORD
