Metadata-Version: 2.1
Name: lumi
Version: 1.0.11
Summary: Convert your Python functions into REST API without any extra effort 🔥
Home-page: https://github.com/Tanmoy741127/lumi
Author: Tanmoy Sarkar
Author-email: ts741127@gmail.com
License: BSD
Keywords: rpc rest api web backend framework
Platform: UNKNOWN
Classifier: Development Status :: 4 - Beta
Classifier: Intended Audience :: Developers
Classifier: Topic :: Software Development :: Libraries :: Python Modules
Classifier: License :: OSI Approved :: BSD License
Classifier: Programming Language :: Python :: 3
Requires-Python: >=3.6
Requires-Dist: nanoid (==2.0.0)
Requires-Dist: waitress (==2.1.2)
